{
  "story": "你發現自己身處一條昏暗的走廊，充滿機器的嗡嗡聲。當你前進時，你偶然發現一扇鎖著的門，通往一個受限區域。你要怎麼做？",
  "actions": [
    {
      "action": "試著駭入門口的安全面板",
      "good": "憑藉你出色的駭客技能，你成功地繞過了安全系統，不被發現，獲得了進入一個隱藏的寶藏的權限。你的科技能力得到了回報。",
      "bad": "在試圖駭入門口的安全系統時，自動防禦系統被觸發。雷射網格啟動，對你造成傷害。寶藏仍然無法取得。"
    },
    {
      "action": "用蠻力強行打開門",
      "good": "憑藉你的全部力量，你成功地撬開了門，發現了一批有價值的物品。你的決心得到了回報。",
      "bad": "你試圖用力打開門，卻觸發了一個隱藏的警報。自動炮塔從牆壁中出現，向你開火，造成傷害。寶藏仍然無法取得。"
    },
    {
      "action": "探索其他路線",
      "good": "小心地探索附近的走廊，你發現了一條隱藏的通道，通往鎖著的門的另一邊。你發現了幫派的隱藏寶藏，自行取走了其中的物品。",
      "bad": "當你尋找其他路線時，不小心觸發了壓力板，引發了一個隱藏的陷阱。有毒氣體開始充滿走廊，對你造成傷害，幸運地逃脫。寶藏仍然無法取得。"
    }
  ]
}