{
  "story": "당신은 거대한 강철 문 앞에 서 있습니다. 문 표면은 긁히고 찌그러져 있습니다. 그 주위의 공기는 기계의 윙윙거림으로 진동하는 것 같습니다. 이 문 뒤에는 갱의 비밀이 숨겨져 있는 무게를 느낄 수 있습니다. 당신은 무엇을 하겠습니까?",
  "actions": [
    {
      "action": "아지트의 내부 시스템에 대한 지식을 사용하여 문 보안을 해제하려고 시도합니다.",
      "good": "몇 초간의 긴장감 속에서 보안 프로토콜을 우회하는 데 성공합니다. 문이 쉭 소리를 내며 열리며, 상자와 크레이트로 가득 찬 방이 드러납니다. 그 안을 뒤지면서 미래의 일에 도움이 될 몇 가지 귀중한 아이템을 찾습니다.",
      "bad": "문 보안을 해제하려는 시도가 경고음을 발생시킵니다. 방이 유독 가스로 가득 차기 시작하며 피해를 입습니다. 최악의 상황은 피하지만, 문은 여전히 당신 뒤에 잠겨 있습니다."
    },
    {
      "action": "힘을 사용하여 문을 강제로 열어보려 합니다.",
      "good": "강력한 포효와 함께 문을 향해 돌진하여 문을 뚫고 들어갑니다. 반대편에는 귀중한 장비와 도구로 가득 찬 방이 있습니다. 당신은 가능한 한 많이 챙깁니다.",
      "bad": "문을 강제로 열려는 시도가 일련의 함정을 작동시킵니다. 문이 뒤에서 쾅 닫히고, 당신은 가시 벽에 직면하게 됩니다. 피해를 입지만 목숨은 건집니다."
    },
    {
      "action": "잠긴 문 주위의 대체 경로를 찾아봅니다.",
      "good": "주변 복도를 조심스럽게 탐색하며 잠긴 문 반대편으로 이어지는 숨겨진 통로를 발견합니다. 그 안을 지나가면서 귀중한 아이템으로 가득 찬 작은 방을 우연히 발견합니다. 당신은 가능한 한 많이 챙깁니다.",
      "bad": "대체 경로를 찾으려는 시도가 끝없이 이어지는 좁은 복도로 당신을 이끕니다. 결국 길을 잃고 혹독한 환경으로 인해 피해를 입습니다."
    }
  ]
}