{
  "story": "사이버펑크 갱 아지트의 깊은 곳에 있으며, 미로처럼 보이는 복도를 헤쳐나가고 있습니다. 갑자기 불길한 비프음이 들리고, 당신의 바이저가 근처의 보안 카메라를 감지합니다. 당신은 어떻게 할까요?",
  "actions": [
    {
      "action": "당신의 해킹 능력으로 카메라를 비활성화합니다",
      "good": "당신의 숙련된 해킹 능력으로 보안 카메라를 감지되지 않게 제거합니다. 당신은 더 이상의 방해 없이 임무를 계속합니다.",
      "bad": "카메라를 비활성화하려는 도중, 실수로 드론 떼를 방출하는 함정을 작동시킵니다. 당신은 무자비하게 공격당하며 피해를 입습니다."
    },
    {
      "action": "카메라를 감지되지 않게 은밀하게 피합니다",
      "good": "당신은 우아하게 카메라를 피해 움직이며, 눈치채지지 않습니다. 당신의 조용한 움직임은 임무를 무사히 수행하는 데 도움이 됩니다.",
      "bad": "카메라를 피하려고 하던 중, 갑자기 움직임을 감지하여 작동합니다. 경보음이 울리며 자동 방어 시스템이 작동하며 당신에게 피해를 입힙니다."
    },
    {
      "action": "카메라를 잔인하게 파괴합니다",
      "good": "폭력적으로 카메라를 부숴버립니다. 당신의 파괴적인 방식으로 가까이 숨겨진 귀중한 아이템을 얻게 됩니다.",
      "bad": "카메라를 파괴하려는 시도가 주변에서 큰 장애를 일으키는 연쇄 반응을 일으킵니다. 혼돈이 일어나며 당신은 피해를 입고 아이템은 손에 넣지 못합니다."
    }
  ]
}