{
  "story": "어두운 실험실에 들어서면, 공기는 먼지로 가득 차 있고 전자기기의 타는 냄새가 납니다. 한때 연구 및 개발에 사용되었던 고장 난 AI 시스템이 근처 작업대에 엉망으로 놓여 있습니다.",
  "actions": [
    {
      "action": "AI 시스템 재부팅 시도",
      "good": "AI 시스템이 갑자기 안정화되며 귀중한 데이터 스트림을 출력하기 시작합니다. 실험실 내 숨겨진 아이템 캐시를 발견합니다.",
      "bad": "AI 시스템 재부팅 시도가 오히려 시스템을 더 불안정하게 만들고, AI가 엉망으로 작동하기 시작합니다. AI의 불규칙한 행동으로 피해를 입습니다."
    },
    {
      "action": "AI 수리를 위한 예비 부품 검색",
      "good": "실험실을 샅샅이 뒤진 끝에, 장비 업그레이드에 사용할 수 있는 희귀하고 귀중한 부품들을 발견합니다.",
      "bad": "예비 부품을 찾는 과정에서 숨겨진 보안 메커니즘이 작동하여 경고음이 울립니다. 자동 방어 시스템으로 인해 피해를 입습니다."
    },
    {
      "action": "AI 시스템 영구적으로 종료",
      "good": "AI 시스템을 종료하자 귀중한 아이템과 데이터가 담긴 숨겨진 공간을 발견합니다.",
      "bad": "AI 시스템의 종료로 인해 일련의 사건들이 연쇄 반응을 일으켜 아지트 전체에 정전이 발생합니다. 생명 유지 시스템에 접근할 수 없어 피해를 입습니다."
    }
  ]
}